fedbone/__init__.py
fedbone-0.0.1a0.dist-info/LICENSE
fedbone-0.0.1a0.dist-info/METADATA
fedbone-0.0.1a0.dist-info/WHEEL
fedbone-0.0.1a0.dist-info/top_level.txt
fedbone-0.0.1a0.dist-info/RECORD
